alchql/__init__.py
alchql/app.py
alchql/batching.py
alchql/consts.py
alchql/converter.py
alchql/enums.py
alchql/fields.py
alchql/get_input_type.py
alchql/gql_fields.py
alchql/gql_id.py
alchql/gql_types.py
alchql/loader_fk.py
alchql/node.py
alchql/query_helper.py
alchql/registry.py
alchql/resolvers.py
alchql/sql_mutation.py
alchql/sqlalchemy_converter.py
alchql/types.py
alchql/utils.py
alchql/connection/__init__.py
alchql/connection/from_array_slice.py
alchql/connection/from_query.py
alchql/connection/utils.py
alchql/extensions/__init__.py
alchql/extensions/extension.py
alchql/extensions/extension_manager.py
alchql/extensions/tracing/InlineTraceExtension.py
alchql/extensions/tracing/TraceTreeBuilder.py
alchql/extensions/tracing/__init__.py
alchql/extensions/tracing/utils.py
alchql/extensions/tracing/generated/__init__.py
alchql/extensions/tracing/generated/reports_pb2.py
alchql/middlewares/__init__.py
alchql/middlewares/debug_middleware.py
alchql/middlewares/loaders_middleware.py
alchql-3.4.10.45323042.dist-info/LICENSE.md
alchql-3.4.10.45323042.dist-info/METADATA
alchql-3.4.10.45323042.dist-info/WHEEL
alchql-3.4.10.45323042.dist-info/top_level.txt
alchql-3.4.10.45323042.dist-info/RECORD
