Metadata-Version: 2.1
Name: alchql
Version: 3.4.10.45323042
Summary: Graphene SQLAlchemy core integration
Home-page: https://github.com/startupmillio/alchql
Author: Yorsh Sergey
Author-email: myrik260138@gmail.com
License: MIT
Keywords: api graphql protocol rest relay graphene
Classifier: Development Status :: 3 - Alpha
Classifier: Intended Audience :: Developers
Classifier: Topic :: Software Development :: Libraries
Classifier: Programming Language :: Python :: 3
Classifier: Programming Language :: Python :: 3.8
Classifier: Programming Language :: Python :: 3.9
License-File: LICENSE.md
Requires-Dist: graphene >=3.0
Requires-Dist: promise >=2.3
Requires-Dist: SQLAlchemy <2,>=1.4
Requires-Dist: aiodataloader ==0.4
Requires-Dist: protobuf
Requires-Dist: setuptools >v62.1.0
Provides-Extra: test
Requires-Dist: pytest <7.0,>=6.2.0 ; extra == 'test'
Requires-Dist: coverage[toml] ; extra == 'test'
Requires-Dist: starlette ; extra == 'test'
Requires-Dist: sqlalchemy-utils <1.0,>=0.37.0 ; extra == 'test'
Requires-Dist: pytest-benchmark <4.0,>=3.4.0 ; extra == 'test'
Requires-Dist: pytest-asyncio <0.18,>=0.17.2 ; extra == 'test'
Requires-Dist: aiosqlite <0.18,>=0.17.0 ; extra == 'test'
Requires-Dist: pytest-cov ; extra == 'test'
Requires-Dist: starlette-graphene3 ; extra == 'test'
